note.py
note.py_gui-1.3.2.dist-info/AUTHORS
note.py_gui-1.3.2.dist-info/LICENSE
note.py_gui-1.3.2.dist-info/METADATA
note.py_gui-1.3.2.dist-info/WHEEL
note.py_gui-1.3.2.dist-info/entry_points.txt
note.py_gui-1.3.2.dist-info/top_level.txt
note.py_gui-1.3.2.dist-info/RECORD
